xencode/__init__.py
xencode/compiler.py
xencode-0.1.0.dist-info/LICENSE
xencode-0.1.0.dist-info/METADATA
xencode-0.1.0.dist-info/WHEEL
xencode-0.1.0.dist-info/entry_points.txt
xencode-0.1.0.dist-info/top_level.txt
xencode-0.1.0.dist-info/RECORD
